weiyu/__init__.py
weiyu/__version__.py
weiyu/adapters/__init__.py
weiyu/adapters/http/__init__.py
weiyu/adapters/http/base.py
weiyu/adapters/http/tornado_.py
weiyu/adapters/http/util.py
weiyu/adapters/http/wsgi.py
weiyu/async/__init__.py
weiyu/async/views.py
weiyu/cache/__init__.py
weiyu/cache/drivers/__init__.py
weiyu/cache/drivers/baseclass.py
weiyu/cache/drivers/memcached_driver.py
weiyu/cache/drivers/redis_driver.py
weiyu/db/__init__.py
weiyu/db/drivers/__init__.py
weiyu/db/drivers/baseclass.py
weiyu/db/drivers/pymongo_driver.py
weiyu/db/drivers/redis_driver.py
weiyu/db/drivers/riak_driver.py
weiyu/db/mapper/__init__.py
weiyu/db/mapper/base.py
weiyu/helpers/__init__.py
weiyu/helpers/annotation.py
weiyu/helpers/hub.py
weiyu/helpers/metaprogramming.py
weiyu/helpers/misc.py
weiyu/helpers/modprober.py
weiyu/helpers/regex_helper.py
weiyu/init/__init__.py
weiyu/init/viewloader.py
weiyu/reflex/__init__.py
weiyu/reflex/classes.py
weiyu/registry/__init__.py
weiyu/registry/classes.py
weiyu/registry/loader.py
weiyu/registry/provider.py
weiyu/rendering/__init__.py
weiyu/rendering/base.py
weiyu/rendering/decorators.py
weiyu/rendering/dummyrenderer.py
weiyu/rendering/exc.py
weiyu/rendering/jsonrenderer.py
weiyu/rendering/makorenderer.py
weiyu/rendering/scssrenderer.py
weiyu/rendering/views.py
weiyu/router/__init__.py
weiyu/router/base.py
weiyu/router/exactrouter.py
weiyu/router/regexrouter.py
weiyu/router/reverser.py
weiyu/router/config/__init__.py
weiyu/router/config/parser.py
weiyu/router/config/wrlex.py
weiyu/router/config/wryacc.py
weiyu/session/__init__.py
weiyu/session/beakerbackend.py
weiyu/session/redisbackend.py
weiyu/shortcuts/__init__.py
weiyu/signals/__init__.py
weiyu/utils/__init__.py
weiyu/utils/decorators.py
weiyu/utils/ghwebhook.py
weiyu/utils/server.py
weiyu/utils/views.py
weiyu-0.2.1.dist-info/DESCRIPTION.rst
weiyu-0.2.1.dist-info/METADATA
weiyu-0.2.1.dist-info/RECORD
weiyu-0.2.1.dist-info/WHEEL
weiyu-0.2.1.dist-info/pydist.json
weiyu-0.2.1.dist-info/top_level.txt
